marketticker/AccountDataConsumer.py
marketticker/AccountDataManager.py
marketticker/AccountListener.py
marketticker/MQListener.py
marketticker/MQPublisher.py
marketticker/MarketDataConsumer.py
marketticker/MarketDataManager.py
marketticker/MarketListener.py
marketticker/Symbol.py
marketticker/__init__.py
marketticker/dockerRunner.py
marketticker/factory.py
marketticker/index.py
ccxt_market_ticker-0.0.1.dist-info/LICENSE
ccxt_market_ticker-0.0.1.dist-info/METADATA
ccxt_market_ticker-0.0.1.dist-info/WHEEL
ccxt_market_ticker-0.0.1.dist-info/entry_points.txt
ccxt_market_ticker-0.0.1.dist-info/top_level.txt
ccxt_market_ticker-0.0.1.dist-info/RECORD
