Metadata-Version: 2.1
Name: ccxt-market-ticker
Version: 0.0.1
Summary: This project uses ccxtpro to stream market data from exchanges. You can use this project to stream market data from exchanges to a queue. You can select which exchanges and which symbols you want to stream. by arguments or by a zookeepernode.
Home-page: https://github.com/donnercody/ccxt-market-ticker
Author: donnercody
Author-email: donnercody86@gmail.com
License: MIT
Classifier: License :: OSI Approved :: MIT License
Classifier: Programming Language :: Python
Classifier: Programming Language :: Python :: 2
Classifier: Programming Language :: Python :: 3
License-File: LICENSE
Requires-Dist: numpy
Requires-Dist: pandas
Requires-Dist: ccxt
Requires-Dist: pytest
Requires-Dist: pika
